{
  "version": "2.1",
  "timestamp": "2026-04-29T20:39:21.998340+00:00",
  "score": 64,
  "decision": "HOLD",
  "decision_text": "Conditii mixte. Acumulare DCA cu prudenta.",
  "conviction": "LOW",
  "conviction_detail": "4 cumpara / 0 vinde / 7 neutru (ponderat: buy 32%, sell 0%)",
  "overrides": [],
  "flags": [],
  "fallback_used": [
    "mvrv_zscore",
    "sopr",
    "nupl",
    "puell_multiple",
    "realized_price",
    "btc_ath"
  ],
  "btc_price": 75651,
  "btc_price_live": 75651,
  "btc_ath": 126208.5,
  "btc_ath_date": "2025-10-06",
  "pct_from_ath": -40.06,
  "internal_score": 0.6436,
  "btc_market_cap": 1513939638607.605,
  "btc_24h_change": -0.95,
  "fear_greed": {
    "value": 26,
    "label": "Fear"
  },
  "coingecko": {
    "total_mcap": 2609058835061.3477,
    "btc_dominance": 58.047008318640266,
    "eth_dominance": 10.35642730253727,
    "mcap_change_24h": -1.1838900652560163
  },
  "derivatives": {
    "timeframe": "1d (7-day avg)",
    "funding_rate": -2.826285714285714e-05,
    "funding_pct": -0.002826,
    "funding_pct_now": 0.003571,
    "oi_value": 7217971115.07,
    "oi_delta_pct_7d": 2.97,
    "ls_ratio": 0.7645,
    "ls_ratio_now": 0.9459,
    "long_pct": 48.61,
    "short_pct": 51.39,
    "taker_buy_vol": 51324.11,
    "taker_sell_vol": 52594.7,
    "taker_ratio": 1.0001,
    "taker_ratio_now": 0.9758,
    "basis_pct": 0.108,
    "spot_price": 75798.68,
    "futures_price": 75880.57366567
  },
  "macro": {
    "vix": 18.81,
    "dxy": 98.95
  },
  "pi_cycle": null,
  "indicators": {},
  "components": {
    "mvrv_zscore": {
      "raw": 0.762,
      "norm": 0.804,
      "weight": 0.14,
      "signal": "CUMPARA",
      "explanation": "Z-Score la 0.76. ≤0 = deep value (✓). ≥7 = cycle top (✓). Praguri Glassnode standard."
    },
    "nupl": {
      "raw": 0.289,
      "norm": 0.488,
      "weight": 0.12,
      "signal": "NEUTRU",
      "phase": "Optimism",
      "explanation": "NUPL la 0.289 - faza: Optimism. <0 = capitulare (✓), >0.75 = euforie (✓)."
    },
    "realized_price": {
      "raw": 53697.0,
      "ratio": 1.409,
      "norm": 0.81,
      "weight": 0.09,
      "signal": "NEUTRU",
      "explanation": "Pret actual / Pret realizat = 1.41x. <1x = sub costul mediu (extrem rar, doar la bottom-uri istorice)."
    },
    "puell_multiple": {
      "raw": 0.732,
      "norm": 0.897,
      "weight": 0.07,
      "signal": "CUMPARA",
      "explanation": "Puell la 0.732. <0.5 = miner capitulation (✓). >4 = miner top (✓)."
    },
    "sopr": {
      "raw": 0.998,
      "norm": 0.513,
      "weight": 0.06,
      "signal": "CUMPARA",
      "explanation": "SOPR la 0.9980. <1 = capitulare (holderii vand in pierdere). >1.05 = profit-taking."
    },
    "fear_greed": {
      "raw": 26,
      "norm": 0.74,
      "weight": 0.06,
      "signal": "NEUTRU",
      "label": "Fear",
      "explanation": "Indicele la 26 (Fear). <15 = panica extrema (✓). >85 = lacomie extrema (✓)."
    },
    "drawdown": {
      "raw": -40.06,
      "norm": 0.501,
      "weight": 0.06,
      "signal": "NEUTRU",
      "explanation": "BTC la -40.1% de la ATH ($126,208). <-75% = bottom istoric."
    },
    "halving_cycle": {
      "days_since_halving": 739,
      "days_to_next_halving": 721,
      "norm": 0.7,
      "weight": 0.05,
      "phase": "Corectie / Acumulare",
      "signal": "CUMPARA",
      "explanation": "739 zile de la halving. Faza: Corectie / Acumulare. Urmatorul halving in ~721 zile."
    },
    "days_from_peak": {
      "days_from_peak": 205,
      "norm": 0.5,
      "weight": 0.04,
      "signal": "NEUTRU",
      "explanation": "205 zile de la ATH. Istoric: bottom-urile la 365-450 zile post-peak."
    },
    "vix": {
      "raw": 18.81,
      "norm": 0.206,
      "weight": 0.04,
      "signal": "NEUTRU",
      "explanation": "VIX la 18.8. >30 = stres pe piete (oportunitate contrarian). <13 = complacency."
    },
    "dxy": {
      "raw": 98.95,
      "norm": 0.552,
      "weight": 0.06,
      "signal": "NEUTRU",
      "explanation": "DXY la 98.95. <100 = dolar slab (favorabil crypto). >105 = dolar puternic."
    }
  },
  "analysis": "SCOR RISC: 64/100. Decizie: HOLD (Conviction: LOW).\n\nMVRV Z-Score: 0.762. Z-Score la 0.76. ≤0 = deep value (✓). ≥7 = cycle top (✓). Praguri Glassnode standard.\nNUPL (Optimism): 0.289. NUPL la 0.289 - faza: Optimism. <0 = capitulare (✓), >0.75 = euforie (✓).\nSOPR: 0.998. SOPR la 0.9980. <1 = capitulare (holderii vand in pierdere). >1.05 = profit-taking.\nPuell Multiple: 0.732. Puell la 0.732. <0.5 = miner capitulation (✓). >4 = miner top (✓).\nRealized Price: 53697.0. Pret actual / Pret realizat = 1.41x. <1x = sub costul mediu (extrem rar, doar la bottom-uri istorice).\nFear & Greed: 26 (Fear).\nDrawdown: -40.06% de la ATH ($126,208).\nHalving: 739 zile de la halving. Faza: Corectie / Acumulare. Urmatorul halving in ~721 zile.\nVIX: 18.81. VIX la 18.8. >30 = stres pe piete (oportunitate contrarian). <13 = complacency.\nDXY: 98.95. DXY la 98.95. <100 = dolar slab (favorabil crypto). >105 = dolar puternic.\n\nAceasta analiza este generata automat si nu constituie sfaturi de investitii."
}